{"stat.useItem.53":4,"stat.useItem.98":15,"stat.flyOneCm":456024,"stat.useItem.44":46,"stat.walkOneCm":75905,"stat.drop":1,"stat.jump":124,"stat.swimOneCm":4186,"stat.useItem.126":142,"stat.useItem.159":176,"stat.playOneMinute":53704,"stat.useItem.139":46,"stat.fallOneCm":3277,"achievement.openInventory":35,"stat.useItem.1":28,"stat.useItem.107":13,"stat.useItem.4":17,"stat.useItem.5":298,"stat.useItem.3":814,"stat.damageTaken":120,"achievement.exploreAllBiomes":{"value":0,"progress":["Beach","Stone Beach","River","Ocean","Taiga","Extreme Hills"]},"stat.diveOneCm":2614}